zetalytics/__init__.py
zetalytics/zetalytics.py
zetalytics-api/__init__.py
zetalytics-api/zetalytics-api.py
zetalytics_api-1.0.1.dist-info/LICENSE
zetalytics_api-1.0.1.dist-info/METADATA
zetalytics_api-1.0.1.dist-info/WHEEL
zetalytics_api-1.0.1.dist-info/top_level.txt
zetalytics_api-1.0.1.dist-info/RECORD
