Metadata-Version: 2.1
Name: zetalytics-api
Version: 1.0.1
Summary: API wrapper for the Zetalytics Zonecruncher API.
Home-page: https://github.com/ZETAlytics/community/tree/master/zetalytics-api/py/
Author: Zetalytics
Author-email: integrations@zetalytics.com
License: UNKNOWN
Platform: UNKNOWN
Classifier: Programming Language :: Python :: 3
Classifier: License :: OSI Approved :: GNU General Public License v3 (GPLv3)
Classifier: Operating System :: OS Independent
Requires-Python: >=3.6
